LICENSE
README.md
setup.cfg
setup.py
milabKafkaAPI/API.py
milabKafkaAPI/__init__.py
milabKafkaAPI.egg-info/PKG-INFO
milabKafkaAPI.egg-info/SOURCES.txt
milabKafkaAPI.egg-info/dependency_links.txt
milabKafkaAPI.egg-info/requires.txt
milabKafkaAPI.egg-info/top_level.txt